python_package/__init__.py
python_package/hello_world.py
pykiwi-0.0.2.dist-info/WHEEL
pykiwi-0.0.2.dist-info/METADATA
pykiwi-0.0.2.dist-info/RECORD
